{
  "name": "Christine Sims",
  "age": 21,
  "address": {
    "street": "Muve River",
    "city": "Irugakab",
    "state": "UT",
    "zip": "69157"
  },
  "contact": {
    "phone": "(982) 917-2646",
    "servicePhone": "800512193"
  },
  "birthday": "1998-09-11T11:26:44.239Z",
  "ip": "154.41.34.89",
  "foo": "bar",
  "profile": {
    "about": "Navali kibara lum cupedeve secove ragi ozcilu li seju biphi milew hujefbo kegacaso ip dalraduju ewbijri madkek erigeog. Ka dekef kud sil iptufi orwogcaw todki vi kabhaf zesdihpov pubaviki log cunak cilugfuh lizbunwi fevcad. Dufes ehi sugfawuv mefiv wevjowwe res aculeh saecfu leceti lagu cekarfu ha toldoriju wajib baho zibowu bob ihediwwir. Wo deb wo fer uzsah cew arurecuj mowwu dav aredi paho side wu. Mobdoeda eculek us bicawew ka hufmet pu kafvewgo fuk tahokge vo ki.",
    "bio": "Dubda olitepduh feweka zu nuv bici jeop juwe ed tak cab mipgo. Otjav aclu ileojo ruakgaf ja rihfa akac pekjukij setmulwes gaj ban agfari wisejec ce. Pof li paite manwokur wacug vo vejero vemsoput utiduzne tejkacoj huuwuruh wicu kuzohapum."
  },
  "apiKey": "fac15d1de7bd0cf1d70e68b41cc044504754ae0b0a8cfac178f64beb63309473",
  "currency": {
    "code": "BIF",
    "name": "Burundi Franc"
  }
}