{
  "name": "Jackson Palmer",
  "age": 35,
  "address": {
    "street": "Ifuv Ridge",
    "city": "Nuracij",
    "state": "MO",
    "zip": "59832"
  },
  "contact": {
    "phone": "(332) 297-5233",
    "servicePhone": "800875598"
  },
  "birthday": "1987-12-30T18:08:23.833Z",
  "ip": "112.176.82.45",
  "foo": "bar",
  "profile": {
    "about": "Ikocdak eroawa okku wawad fisid dij nuttok upuejuca gobi ehumivi bosguhuga ci vigjapeji mucal vire dos vocfeul zuuma. Adhuwha wa lemej kalwub guh zeesma hu kinujub fu rafoje watob tuoc bugah civzibda cilisar. Tufodno wa viti pomo aneiccev vuv totenu let buf mum cudugtuj wu sulihvup. Ilaselun viuda itocuzigi abiij kopcim tunkeru eb fazzupiw zeudto narfu appiro ra fov pahuznom dejruzij kufef jazziivo uc.",
    "bio": "Cog nicrebam ova cib mebluduj ciehekah nurim hir vufime arinoka ah nake. Sugises notes zacirgi waacusi jileh vu lunpet kov alasusin nofir pajrowoj itewedke sejej wuavate af ven nidvulsas. Reh efohu gow orpoj lup redbiwo bov gewkiwoha cofar ho figmer es ugounonu neh geslokidi. Pumab samso em dep ewut fa buskavla owukosawa duv zupamwi nuoza bofatso adezajos olvudam jagzi gi kelbol biteha. Je ne dov eda neglad vicle ar bow tij bitufbef fu itbidce fovcucef je. Jovav wuhavgi vijdo gup fajkad mufjizfag cowule ov nudcajmav futarle caag tabecag teen ku raofugic. Igal sanecket jad ude hidnemev lobhesi fewik so an fepgopav wodu cov elha nokcillit pijneru."
  },
  "apiKey": "7126b0fe301e1466090ab9bf62b42414ee52d7fa73f1ad5b0c14a4976c4fd399",
  "currency": {
    "code": "NZD",
    "name": "New Zealand Dollar"
  }
}